odoo/addons/default_multi_user/README.rst
odoo/addons/default_multi_user/__init__.py
odoo/addons/default_multi_user/__manifest__.py
odoo/addons/default_multi_user/hooks.py
odoo/addons/default_multi_user/i18n/default_multi_user.pot
odoo/addons/default_multi_user/models/__init__.py
odoo/addons/default_multi_user/models/ir_default.py
odoo/addons/default_multi_user/readme/CONFIGURE.rst
odoo/addons/default_multi_user/readme/CONTRIBUTORS.rst
odoo/addons/default_multi_user/readme/DESCRIPTION.rst
odoo/addons/default_multi_user/static/description/icon.png
odoo/addons/default_multi_user/static/description/index.html
odoo/addons/default_multi_user/tests/__init__.py
odoo/addons/default_multi_user/tests/test_default_multi_user.py
odoo/addons/default_multi_user/views/ir_default_view.xml
odoo13_addon_default_multi_user-13.0.1.0.1.dist-info/METADATA
odoo13_addon_default_multi_user-13.0.1.0.1.dist-info/WHEEL
odoo13_addon_default_multi_user-13.0.1.0.1.dist-info/top_level.txt
odoo13_addon_default_multi_user-13.0.1.0.1.dist-info/RECORD
